img_compress2/__init__.py
img_compress2/compress.py
img_compress2-1.dist-info/LICENSE
img_compress2-1.dist-info/METADATA
img_compress2-1.dist-info/WHEEL
img_compress2-1.dist-info/top_level.txt
img_compress2-1.dist-info/RECORD
