Metadata-Version: 2.1
Name: img-compress2
Version: 1
Summary: Try_一个主流图片压缩方案的自动化脚本(利用 tinify 实现666)
Author-email: Jay <jaylcy2022@gmail.com>
Project-URL: Homepage, https://ilovefishc.com
Project-URL: Bug Tracker, https://fishc.com.cn
Classifier: Programming Language :: Python :: 3
Classifier: License :: OSI Approved :: MIT License
Classifier: Operating System :: OS Independent
Requires-Python: >=3.6
License-File: LICENSE
Requires-Dist: tinify
